{
  "multipart": [
    {
      "when": {
        "facing": "north"
      },
      "apply": {
        "model": "londonunderground:block/block_roundel_station",
        "y": 180
      }
    },
    {
      "when": {
        "facing": "east"
      },
      "apply": {
        "model": "londonunderground:block/block_roundel_station",
        "y": -90
      }
    },
    {
      "when": {
        "facing": "south"
      },
      "apply": {
        "model": "londonunderground:block/block_roundel_station"
      }
    },
    {
      "when": {
        "facing": "west"
      },
      "apply": {
        "model": "londonunderground:block/block_roundel_station",
        "y": 90
      }
    }
  ]
}